LICENSE
README.md
pyproject.toml
setup.py
src/pyquirrinds/__init__.py
src/pyquirrinds/funciones.py
src/pyquirrinds.egg-info/PKG-INFO
src/pyquirrinds.egg-info/SOURCES.txt
src/pyquirrinds.egg-info/dependency_links.txt
src/pyquirrinds.egg-info/requires.txt
src/pyquirrinds.egg-info/top_level.txt