Metadata-Version: 2.1
Name: pyquirrinds
Version: 0.0.1
Summary: Librería para limpieza y visualización de datos, y Machine learning
Home-page: https://github.com/LLBF/Proyecto_libreria_DS
Author: Clase Data Science The Bridge Septiembre 2022
License: MIT
Classifier: Programming Language :: Python :: 3
Classifier: License :: OSI Approved :: MIT License
Requires-Python: >=3.7
License-File: LICENSE
